{
  "gfx/tiles/ashland": "Ash land",
  "gfx/tiles/beach": "Beach",
  "gfx/tiles/beechgrove": "Beech grove",
  "gfx/tiles/bluesod": "Blue sod",
  "gfx/tiles/boards": "Boards",
  "gfx/tiles/bog": "Bog",
  "gfx/tiles/bogwater": "Bog water",
  "gfx/tiles/bountyacre": "Bounty acre",
  "gfx/tiles/cave": "Cave",
  "gfx/tiles/cloudrange": "Cloud range",
  "gfx/tiles/deep": "Deep water",
  "gfx/tiles/deeptangle": "Deep tangle",
  "gfx/tiles/dirt": "Dirt",
  "gfx/tiles/dryflat": "Dry flat",
  "gfx/tiles/dryweald": "Dry weald",
  "gfx/tiles/fen": "Fen",
  "gfx/tiles/fenwater": "Fen water",
  "gfx/tiles/field": "Field",
  "gfx/tiles/flowermeadow": "Flower meadow",
  "gfx/tiles/gleamgrotto": "Gleam grotto",
  "gfx/tiles/grass": "Grass",
  "gfx/tiles/greenbrake": "Green brake",
  "gfx/tiles/greensward": "Greens ward",
  "gfx/tiles/hardsteppe": "Hard steppe",
  "gfx/tiles/heath": "Heath",
  "gfx/tiles/highground": "High ground",
  "gfx/tiles/leaf": "Leaf",
  "gfx/tiles/leafpatch": "Leaf patch",
  "gfx/tiles/lichenwold": "Lichen wold",
  "gfx/tiles/lushcave": "Lush cave",
  "gfx/tiles/lushfield": "Lush field",
  "gfx/tiles/mine": "Mine",
  "gfx/tiles/moor": "Moor",
  "gfx/tiles/mountain": "Mountain",
  "gfx/tiles/mountainsnow": "Mountain snow",
  "gfx/tiles/nil": "Nil",
  "gfx/tiles/oakwilds": "Oak wilds",
  "gfx/tiles/odeep": "Deep ocean",
  "gfx/tiles/odeeper": "Very deep ocean",
  "gfx/tiles/owater": "Ocean",
  "gfx/tiles/oxpasture": "Ox pasture",
  "gfx/tiles/paving/acrebrick": "Acre brick",
  "gfx/tiles/paving/alabaster": "Alabaster (paved)",
  "gfx/tiles/paving/apatite": "Apatite (paved)",
  "gfx/tiles/paving/arkose": "Arkose (paved)",
  "gfx/tiles/paving/ballbrick": "Ball brick",
  "gfx/tiles/paving/basalt": "Basalt (paved)",
  "gfx/tiles/paving/breccia": "Breccia (paved)",
  "gfx/tiles/paving/catgold": "Catgold (paved)",
  "gfx/tiles/paving/diabase": "Diabase (paved)",
  "gfx/tiles/paving/diorite": "Diorite (paved)",
  "gfx/tiles/paving/dolomite": "Dolomite (paved)",
  "gfx/tiles/paving/eclogite": "Eclogite (paved)",
  "gfx/tiles/paving/feldspar": "Feldspar (paved)",
  "gfx/tiles/paving/flint": "Flint (paved)",
  "gfx/tiles/paving/fluorospar": "Fluorospar (paved)",
  "gfx/tiles/paving/gabbro": "Gabbro (paved)",
  "gfx/tiles/paving/gneiss": "Gneiss (paved)",
  "gfx/tiles/paving/granite": "Granite (paved)",
  "gfx/tiles/paving/greenschist": "Greenschist (paved)",
  "gfx/tiles/paving/hornblende": "Hornblende (paved)",
  "gfx/tiles/paving/kyanite": "Kyanite (paved)",
  "gfx/tiles/paving/limestone": "Limestone (paved)",
  "gfx/tiles/paving/marble": "Marble (paved)",
  "gfx/tiles/paving/mica": "Mica (paved)",
  "gfx/tiles/paving/microlite": "Microlite (paved)",
  "gfx/tiles/paving/olivine": "Olivine (paved)",
  "gfx/tiles/paving/orthoclase": "Orthoclase (paved)",
  "gfx/tiles/paving/pegmatite": "Pegmatite (paved)",
  "gfx/tiles/paving/porphyry": "Porphyry (paved)",
  "gfx/tiles/paving/pumice": "Pumice (paved)",
  "gfx/tiles/paving/quarryquartz": "Quarryquartz (paved)",
  "gfx/tiles/paving/quartz": "Quartz (paved)",
  "gfx/tiles/paving/rhyolite": "Rhyolite (paved)",
  "gfx/tiles/paving/sandstone": "Sandstone (paved)",
  "gfx/tiles/paving/slag": "Slag (paved)",
  "gfx/tiles/paving/slate": "Slate (paved)",
  "gfx/tiles/paving/soapstone": "Soapstone (paved)",
  "gfx/tiles/paving/sodalite": "Sodalite (paved)",
  "gfx/tiles/paving/zincspar": "Zincspar (paved)",
  "gfx/tiles/pinebarren": "Pine barren",
  "gfx/tiles/redplain": "Red plain",
  "gfx/tiles/rockbeach": "Rock beach",
  "gfx/tiles/rocks/alabaster": "Alabaster",
  "gfx/tiles/rocks/apatite": "Apatite",
  "gfx/tiles/rocks/argentite": "Argentite (Silvershine)",
  "gfx/tiles/rocks/arkose": "Arkose",
  "gfx/tiles/rocks/basalt": "Basalt",
  "gfx/tiles/rocks/blackcoal": "Black coal",
  "gfx/tiles/rocks/breccia": "Breccia",
  "gfx/tiles/rocks/cassiterite": "Cassiterite",
  "gfx/tiles/rocks/chalcopyrite": "Chalcopyrite",
  "gfx/tiles/rocks/cinnabar": "Cinnabar",
  "gfx/tiles/rocks/diabase": "Diabase",
  "gfx/tiles/rocks/diorite": "Diorite",
  "gfx/tiles/rocks/dolomite": "Dolomite",
  "gfx/tiles/rocks/eclogite": "Eclogite",
  "gfx/tiles/rocks/feldspar": "Feldspar",
  "gfx/tiles/rocks/flint": "Flint",
  "gfx/tiles/rocks/fluorospar": "Fluorospar",
  "gfx/tiles/rocks/gabbro": "Gabbro",
  "gfx/tiles/rocks/galena": "Galena",
  "gfx/tiles/rocks/gneiss": "Gneiss",
  "gfx/tiles/rocks/granite": "Granite",
  "gfx/tiles/rocks/greenschist": "Greenschist",
  "gfx/tiles/rocks/hematite": "Hematite (Bloodstone)",
  "gfx/tiles/rocks/hornblende": "Hornblende",
  "gfx/tiles/rocks/hornsilver": "Horn silver",
  "gfx/tiles/rocks/ilmenite": "Ilmenite (Heavy earth)",
  "gfx/tiles/rocks/kyanite": "Kyanite",
  "gfx/tiles/rocks/leadglance": "Leadglance",
  "gfx/tiles/rocks/limestone": "Limestone",
  "gfx/tiles/rocks/limonite": "Limonite (Iron ochre)",
  "gfx/tiles/rocks/magnetite": "Magnetite (Black ore)",
  "gfx/tiles/rocks/malachite": "Malachite",
  "gfx/tiles/rocks/marble": "Marble",
  "gfx/tiles/rocks/mica": "Mica",
  "gfx/tiles/rocks/microlite": "Microlite",
  "gfx/tiles/rocks/nagyagite": "Nagyagite (Leaf ore)",
  "gfx/tiles/rocks/olivine": "Olivine",
  "gfx/tiles/rocks/orthoclase": "Orthoclase",
  "gfx/tiles/rocks/pegmatite": "Pegmatite",
  "gfx/tiles/rocks/petzite": "Petzite (Direvein)",
  "gfx/tiles/rocks/porphyry": "Porphyry",
  "gfx/tiles/rocks/pumice": "Pumice",
  "gfx/tiles/rocks/quartz": "Quartz",
  "gfx/tiles/rocks/rhyolite": "Rhyolite",
  "gfx/tiles/rocks/sandstone": "Sandstone",
  "gfx/tiles/rocks/schist": "Schist",
  "gfx/tiles/rocks/slate": "Slate",
  "gfx/tiles/rocks/soapstone": "Soapstone",
  "gfx/tiles/rocks/sodalite": "Sodalite",
  "gfx/tiles/rocks/sylvanite": "Sylvanite (Schrifterz)",
  "gfx/tiles/rocks/zincspar": "Zincspar",
  "gfx/tiles/rootbosk": "Root bosk",
  "gfx/tiles/sandcliff": "Sand cliff",
  "gfx/tiles/scrubveld": "Scrub veld",
  "gfx/tiles/seabed": "Seabed",
  "gfx/tiles/shadehollow": "Shade hollow",
  "gfx/tiles/shadycopse": "Shady copse",
  "gfx/tiles/skargard": "Skargard",
  "gfx/tiles/sombrebramble": "Sombre bramble",
  "gfx/tiles/sourtimber": "Sour timber",
  "gfx/tiles/spave": "Spave",
  "gfx/tiles/swamp": "Swamp",
  "gfx/tiles/swampwater": "Swamp water",
  "gfx/tiles/wald": "Wald",
  "gfx/tiles/warmdepth": "Warm depth",
  "gfx/tiles/water": "Water",
  "gfx/tiles/wildmoor": "Wild moor",
  "gfx/tiles/timberland": "Timberland",
  "gfx/tiles/blackwood": "Black Wood",
  "gfx/tiles/peatmoss": "Peat Moss",
  "gfx/tiles/wildturf": "Wild Turf"
}
